biography/__init__.py
biography/apps.py
biography/conf.py
biography/fields.py
biography/pagination.py
biography/urls.py
biography/widgets.py
biography/admin/__init__.py
biography/admin/biography.py
biography/admin/quote.py
biography/migrations/0001_initial.py
biography/migrations/0002_auto_20180118_1515.py
biography/migrations/0003_auto_20181127_1941.py
biography/migrations/0004_education_graduation_date.py
biography/migrations/0005_education_degree_program.py
biography/migrations/0006_residence.py
biography/migrations/0007_auto_20181207_1651.py
biography/migrations/0008_financials_notes.py
biography/migrations/0009_auto_20181221_1945.py
biography/migrations/0010_pastcampaign.py
biography/migrations/__init__.py
biography/models/__init__.py
biography/models/biography.py
biography/models/birthplace.py
biography/models/education.py
biography/models/financials.py
biography/models/ideology.py
biography/models/legislation.py
biography/models/occupation.py
biography/models/past_campaign.py
biography/models/publication.py
biography/models/quote.py
biography/models/residence.py
biography/serializers/__init__.py
biography/serializers/biography.py
biography/serializers/birthplace.py
biography/serializers/education.py
biography/serializers/financials.py
biography/serializers/ideology.py
biography/serializers/ideology_category.py
biography/serializers/legislation.py
biography/serializers/occupation.py
biography/serializers/publication.py
biography/serializers/quote.py
biography/serializers/quote_topic.py
biography/utils/__init__.py
biography/utils/importers.py
biography/viewsets/__init__.py
biography/viewsets/base.py
biography/viewsets/biography.py
biography/viewsets/birthplace.py
biography/viewsets/education.py
biography/viewsets/financials.py
biography/viewsets/ideology.py
biography/viewsets/ideology_category.py
biography/viewsets/legislation.py
biography/viewsets/occupation.py
biography/viewsets/publication.py
biography/viewsets/quote.py
biography/viewsets/quote_topic.py
politico_civic_biography-0.2.2.dist-info/LICENSE
politico_civic_biography-0.2.2.dist-info/METADATA
politico_civic_biography-0.2.2.dist-info/WHEEL
politico_civic_biography-0.2.2.dist-info/top_level.txt
politico_civic_biography-0.2.2.dist-info/RECORD
